FGTSA/FGTSA.py
FGTSA/FGTSAUtils.py
FGTSA/N4FCM_Module.py
FGTSA-1.0.2.dist-info/LICENSE.txt
FGTSA-1.0.2.dist-info/METADATA
FGTSA-1.0.2.dist-info/WHEEL
FGTSA-1.0.2.dist-info/top_level.txt
FGTSA-1.0.2.dist-info/RECORD
