Metadata-Version: 2.1
Name: FGTSA
Version: 1.0.2
Summary: A toolkit for medical image subregion analysis
Home-page: https://github.com/GDPHMediaLab/FGTSA
Author: Media Lab
Author-email: shizhenwei@gdph.org.cn
Classifier: Programming Language :: Python :: 3.7
Classifier: License :: OSI Approved :: MIT License
Classifier: Operating System :: OS Independent
License-File: LICENSE.txt
